aranda/__init__.py
aranda-0.1.0.dist-info/METADATA
aranda-0.1.0.dist-info/WHEEL
aranda-0.1.0.dist-info/entry_points.txt
aranda-0.1.0.dist-info/RECORD
